{
  "fio version" : "fio-3.16",
  "timestamp" : 1759925748,
  "timestamp_ms" : 1759925748554,
  "time" : "Wed Oct  8 21:15:48 2025",
  "global options" : {
    "bs" : "128k",
    "numjobs" : "8",
    "time_based" : "1",
    "runtime" : "30s",
    "randrepeat" : "1",
    "random_generator" : "lfsr",
    "randseed" : "1",
    "refill_buffers" : "1",
    "norandommap" : "1",
    "group_reporting" : "1",
    "lat_percentiles" : "1",
    "ioengine" : "psync",
    "direct" : "0",
    "iodepth" : "1",
    "group_reporting" : "1",
    "end_fsync" : "1",
    "directory" : "/mnt/test/"
  },
  "jobs" : [
    {
      "jobname" : "randread",
      "groupid" : 0,
      "error" : 0,
      "eta" : 0,
      "elapsed" : 31,
      "job options" : {
        "rw" : "randread"
      },
      "read" : {
        "io_bytes" : 316947562496,
        "io_kbytes" : 309519104,
        "bw_bytes" : 10564566597,
        "bw" : 10316959,
        "iops" : 80601.246625,
        "runtime" : 30001,
        "total_ios" : 2418118,
        "short_ios" : 0,
        "drop_ios" : 0,
        "slat_ns" : {
          "min" : 0,
          "max" : 0,
          "mean" : 0.000000,
          "stddev" : 0.000000
        },
        "clat_ns" : {
          "min" : 40735,
          "max" : 9087237,
          "mean" : 90000.301995,
          "stddev" : 57467.688830
        },
        "lat_ns" : {
          "min" : 40763,
          "max" : 9088336,
          "mean" : 90046.668522,
          "stddev" : 57470.258936,
          "percentile" : {
            "1.000000" : 58112,
            "5.000000" : 63744,
            "10.000000" : 67072,
            "20.000000" : 72192,
            "30.000000" : 75264,
            "40.000000" : 78336,
            "50.000000" : 81408,
            "60.000000" : 84480,
            "70.000000" : 87552,
            "80.000000" : 91648,
            "90.000000" : 96768,
            "95.000000" : 108032,
            "99.000000" : 419840,
            "99.500000" : 468992,
            "99.900000" : 561152,
            "99.950000" : 610304,
            "99.990000" : 790528
          },
          "bins" : {
            "40704" : 1,
            "41216" : 1,
            "41728" : 1,
            "43264" : 1,
            "43776" : 1,
            "44800" : 1,
            "45312" : 2,
            "45824" : 4,
            "46336" : 3,
            "46848" : 9,
            "47360" : 16,
            "47872" : 19,
            "48384" : 41,
            "48896" : 54,
            "49408" : 99,
            "49920" : 122,
            "50432" : 168,
            "50944" : 243,
            "51456" : 316,
            "51968" : 355,
            "52480" : 489,
            "52992" : 683,
            "53504" : 797,
            "54016" : 931,
            "54528" : 1187,
            "55040" : 1491,
            "55552" : 1837,
            "56064" : 2229,
            "56576" : 2524,
            "57088" : 3093,
            "57600" : 3736,
            "58112" : 4218,
            "58624" : 4919,
            "59136" : 5631,
            "59648" : 6390,
            "60160" : 7471,
            "60672" : 8246,
            "61184" : 9233,
            "61696" : 10127,
            "62208" : 11291,
            "62720" : 12168,
            "63232" : 13200,
            "63744" : 14376,
            "64256" : 15640,
            "64768" : 16494,
            "65280" : 17829,
            "66048" : 39556,
            "67072" : 44148,
            "68096" : 48596,
            "69120" : 52956,
            "70144" : 57323,
            "71168" : 61582,
            "72192" : 65804,
            "73216" : 69961,
            "74240" : 74117,
            "75264" : 78386,
            "76288" : 81889,
            "77312" : 84421,
            "78336" : 86372,
            "79360" : 86294,
            "80384" : 85013,
            "81408" : 83960,
            "82432" : 81745,
            "83456" : 79590,
            "84480" : 76842,
            "85504" : 75871,
            "86528" : 73814,
            "87552" : 71448,
            "88576" : 68360,
            "89600" : 64947,
            "90624" : 60610,
            "91648" : 55749,
            "92672" : 50075,
            "93696" : 44164,
            "94720" : 38065,
            "95744" : 32387,
            "96768" : 26853,
            "97792" : 22310,
            "98816" : 18455,
            "99840" : 15318,
            "100864" : 12538,
            "101888" : 10199,
            "102912" : 8769,
            "103936" : 7654,
            "104960" : 6879,
            "105984" : 6094,
            "107008" : 5534,
            "108032" : 5192,
            "109056" : 4732,
            "110080" : 4526,
            "111104" : 4248,
            "112128" : 3887,
            "113152" : 3678,
            "114176" : 3445,
            "115200" : 3172,
            "116224" : 2958,
            "117248" : 2613,
            "118272" : 2505,
            "119296" : 2203,
            "120320" : 1904,
            "121344" : 1750,
            "122368" : 1590,
            "123392" : 1405,
            "124416" : 1215,
            "125440" : 1093,
            "126464" : 969,
            "127488" : 812,
            "128512" : 752,
            "129536" : 625,
            "130560" : 538,
            "132096" : 895,
            "134144" : 662,
            "136192" : 506,
            "138240" : 372,
            "140288" : 336,
            "142336" : 238,
            "144384" : 183,
            "146432" : 158,
            "148480" : 122,
            "150528" : 86,
            "152576" : 58,
            "154624" : 46,
            "156672" : 50,
            "158720" : 33,
            "160768" : 30,
            "162816" : 20,
            "164864" : 18,
            "166912" : 22,
            "168960" : 10,
            "171008" : 6,
            "173056" : 12,
            "175104" : 9,
            "177152" : 9,
            "179200" : 14,
            "181248" : 12,
            "183296" : 8,
            "185344" : 5,
            "187392" : 6,
            "189440" : 8,
            "191488" : 9,
            "193536" : 17,
            "195584" : 13,
            "197632" : 18,
            "199680" : 8,
            "201728" : 20,
            "203776" : 26,
            "205824" : 23,
            "207872" : 32,
            "209920" : 38,
            "211968" : 35,
            "214016" : 31,
            "216064" : 46,
            "218112" : 38,
            "220160" : 50,
            "222208" : 44,
            "224256" : 37,
            "226304" : 59,
            "228352" : 46,
            "230400" : 79,
            "232448" : 54,
            "234496" : 69,
            "236544" : 75,
            "238592" : 90,
            "240640" : 81,
            "242688" : 97,
            "244736" : 108,
            "246784" : 107,
            "248832" : 117,
            "250880" : 116,
            "252928" : 116,
            "254976" : 156,
            "257024" : 111,
            "259072" : 149,
            "261120" : 160,
            "264192" : 305,
            "268288" : 362,
            "272384" : 400,
            "276480" : 439,
            "280576" : 491,
            "284672" : 545,
            "288768" : 574,
            "292864" : 615,
            "296960" : 705,
            "301056" : 677,
            "305152" : 778,
            "309248" : 808,
            "313344" : 886,
            "317440" : 916,
            "321536" : 1059,
            "325632" : 1012,
            "329728" : 1120,
            "333824" : 1116,
            "337920" : 1187,
            "342016" : 1220,
            "346112" : 1320,
            "350208" : 1256,
            "354304" : 1284,
            "358400" : 1345,
            "362496" : 1369,
            "366592" : 1412,
            "370688" : 1404,
            "374784" : 1380,
            "378880" : 1370,
            "382976" : 1447,
            "387072" : 1413,
            "391168" : 1330,
            "395264" : 1368,
            "399360" : 1406,
            "403456" : 1338,
            "407552" : 1339,
            "411648" : 1276,
            "415744" : 1192,
            "419840" : 1221,
            "423936" : 1163,
            "428032" : 1126,
            "432128" : 1139,
            "436224" : 1053,
            "440320" : 1012,
            "444416" : 980,
            "448512" : 1000,
            "452608" : 910,
            "456704" : 835,
            "460800" : 750,
            "464896" : 724,
            "468992" : 780,
            "473088" : 679,
            "477184" : 669,
            "481280" : 656,
            "485376" : 582,
            "489472" : 548,
            "493568" : 557,
            "497664" : 487,
            "501760" : 462,
            "505856" : 475,
            "509952" : 429,
            "514048" : 430,
            "518144" : 369,
            "522240" : 353,
            "528384" : 633,
            "536576" : 534,
            "544768" : 493,
            "552960" : 439,
            "561152" : 395,
            "569344" : 312,
            "577536" : 240,
            "585728" : 217,
            "593920" : 186,
            "602112" : 191,
            "610304" : 144,
            "618496" : 124,
            "626688" : 114,
            "634880" : 91,
            "643072" : 70,
            "651264" : 67,
            "659456" : 47,
            "667648" : 51,
            "675840" : 54,
            "684032" : 28,
            "692224" : 37,
            "700416" : 29,
            "708608" : 31,
            "716800" : 24,
            "724992" : 20,
            "733184" : 18,
            "741376" : 19,
            "749568" : 18,
            "757760" : 19,
            "765952" : 10,
            "774144" : 5,
            "782336" : 5,
            "790528" : 10,
            "798720" : 10,
            "806912" : 5,
            "815104" : 7,
            "823296" : 12,
            "831488" : 8,
            "839680" : 13,
            "847872" : 6,
            "856064" : 8,
            "864256" : 9,
            "872448" : 7,
            "880640" : 5,
            "888832" : 8,
            "897024" : 7,
            "905216" : 7,
            "913408" : 5,
            "921600" : 7,
            "929792" : 4,
            "937984" : 4,
            "946176" : 7,
            "954368" : 1,
            "962560" : 5,
            "970752" : 4,
            "978944" : 5,
            "987136" : 3,
            "995328" : 2,
            "1003520" : 3,
            "1011712" : 2,
            "1019904" : 3,
            "1028096" : 3,
            "1036288" : 1,
            "1044480" : 1,
            "1056768" : 4,
            "1073152" : 4,
            "1089536" : 4,
            "1105920" : 6,
            "1122304" : 2,
            "1138688" : 3,
            "1155072" : 2,
            "1171456" : 5,
            "1187840" : 1,
            "1204224" : 1,
            "1220608" : 5,
            "1236992" : 3,
            "1253376" : 1,
            "1269760" : 3,
            "1286144" : 1,
            "1318912" : 1,
            "1335296" : 1,
            "1384448" : 2,
            "1400832" : 1,
            "1417216" : 1,
            "1449984" : 1,
            "1564672" : 1,
            "8093696" : 1,
            "8224768" : 2,
            "8290304" : 1,
            "8585216" : 1,
            "8716288" : 3,
            "9109504" : 1
          }
        },
        "bw_min" : 2483968,
        "bw_max" : 14149519,
        "bw_agg" : 99.804067,
        "bw_mean" : 10296744.661017,
        "bw_dev" : 365283.967095,
        "bw_samples" : 472,
        "iops_min" : 19406,
        "iops_max" : 110543,
        "iops_mean" : 80443.169492,
        "iops_stddev" : 2853.772099,
        "iops_samples" : 472
      },
      "write" : {
        "io_bytes" : 0,
        "io_kbytes" : 0,
        "bw_bytes" : 0,
        "bw" : 0,
        "iops" : 0.000000,
        "runtime" : 0,
        "total_ios" : 0,
        "short_ios" : 0,
        "drop_ios" : 0,
        "slat_ns" : {
          "min" : 0,
          "max" : 0,
          "mean" : 0.000000,
          "stddev" : 0.000000
        },
        "clat_ns" : {
          "min" : 0,
          "max" : 0,
          "mean" : 0.000000,
          "stddev" : 0.000000
        },
        "lat_ns" : {
          "min" : 0,
          "max" : 0,
          "mean" : 0.000000,
          "stddev" : 0.000000,
          "percentile" : {
            "1.000000" : 0,
            "5.000000" : 0,
            "10.000000" : 0,
            "20.000000" : 0,
            "30.000000" : 0,
            "40.000000" : 0,
            "50.000000" : 0,
            "60.000000" : 0,
            "70.000000" : 0,
            "80.000000" : 0,
            "90.000000" : 0,
            "95.000000" : 0,
            "99.000000" : 0,
            "99.500000" : 0,
            "99.900000" : 0,
            "99.950000" : 0,
            "99.990000" : 0
          },
          "bins" : {

          }
        },
        "bw_min" : 0,
        "bw_max" : 0,
        "bw_agg" : 0.000000,
        "bw_mean" : 0.000000,
        "bw_dev" : 0.000000,
        "bw_samples" : 0,
        "iops_min" : 0,
        "iops_max" : 0,
        "iops_mean" : 0.000000,
        "iops_stddev" : 0.000000,
        "iops_samples" : 0
      },
      "trim" : {
        "io_bytes" : 0,
        "io_kbytes" : 0,
        "bw_bytes" : 0,
        "bw" : 0,
        "iops" : 0.000000,
        "runtime" : 0,
        "total_ios" : 0,
        "short_ios" : 0,
        "drop_ios" : 0,
        "slat_ns" : {
          "min" : 0,
          "max" : 0,
          "mean" : 0.000000,
          "stddev" : 0.000000
        },
        "clat_ns" : {
          "min" : 0,
          "max" : 0,
          "mean" : 0.000000,
          "stddev" : 0.000000
        },
        "lat_ns" : {
          "min" : 0,
          "max" : 0,
          "mean" : 0.000000,
          "stddev" : 0.000000,
          "percentile" : {
            "1.000000" : 0,
            "5.000000" : 0,
            "10.000000" : 0,
            "20.000000" : 0,
            "30.000000" : 0,
            "40.000000" : 0,
            "50.000000" : 0,
            "60.000000" : 0,
            "70.000000" : 0,
            "80.000000" : 0,
            "90.000000" : 0,
            "95.000000" : 0,
            "99.000000" : 0,
            "99.500000" : 0,
            "99.900000" : 0,
            "99.950000" : 0,
            "99.990000" : 0
          },
          "bins" : {

          }
        },
        "bw_min" : 0,
        "bw_max" : 0,
        "bw_agg" : 0.000000,
        "bw_mean" : 0.000000,
        "bw_dev" : 0.000000,
        "bw_samples" : 0,
        "iops_min" : 0,
        "iops_max" : 0,
        "iops_mean" : 0.000000,
        "iops_stddev" : 0.000000,
        "iops_samples" : 0
      },
      "sync" : {
        "lat_ns" : {
          "min" : 0,
          "max" : 0,
          "mean" : 0.000000,
          "stddev" : 0.000000
        },
        "total_ios" : 0
      },
      "job_runtime" : 240000,
      "usr_cpu" : 0.747083,
      "sys_cpu" : 51.880000,
      "ctx" : 2422742,
      "majf" : 0,
      "minf" : 328,
      "iodepth_level" : {
        "1" : 100.000000,
        "2" : 0.000000,
        "4" : 0.000000,
        "8" : 0.000000,
        "16" : 0.000000,
        "32" : 0.000000,
        ">=64" : 0.000000
      },
      "iodepth_submit" : {
        "0" : 0.000000,
        "4" : 100.000000,
        "8" : 0.000000,
        "16" : 0.000000,
        "32" : 0.000000,
        "64" : 0.000000,
        ">=64" : 0.000000
      },
      "iodepth_complete" : {
        "0" : 0.000000,
        "4" : 100.000000,
        "8" : 0.000000,
        "16" : 0.000000,
        "32" : 0.000000,
        "64" : 0.000000,
        ">=64" : 0.000000
      },
      "latency_ns" : {
        "2" : 0.000000,
        "4" : 0.000000,
        "10" : 0.000000,
        "20" : 0.000000,
        "50" : 0.000000,
        "100" : 0.000000,
        "250" : 0.000000,
        "500" : 0.000000,
        "750" : 0.000000,
        "1000" : 0.000000
      },
      "latency_us" : {
        "2" : 0.000000,
        "4" : 0.000000,
        "10" : 0.000000,
        "20" : 0.000000,
        "50" : 0.013688,
        "100" : 92.224780,
        "250" : 5.091770,
        "500" : 2.364111,
        "750" : 0.293617,
        "1000" : 0.010000
      },
      "latency_ms" : {
        "2" : 0.010000,
        "4" : 0.000000,
        "10" : 0.010000,
        "20" : 0.000000,
        "50" : 0.000000,
        "100" : 0.000000,
        "250" : 0.000000,
        "500" : 0.000000,
        "750" : 0.000000,
        "1000" : 0.000000,
        "2000" : 0.000000,
        ">=2000" : 0.000000
      },
      "latency_depth" : 1,
      "latency_target" : 0,
      "latency_percentile" : 100.000000,
      "latency_window" : 0
    }
  ]
}
